ucamwebauth/__init__.py
ucamwebauth/backends.py
ucamwebauth/exceptions.py
ucamwebauth/middleware.py
ucamwebauth/models.py
ucamwebauth/tests.py
ucamwebauth/urls.py
ucamwebauth/utils.py
ucamwebauth/views.py
ucamwebauth/migrations/0001_initial.py
ucamwebauth/migrations/__init__.py
ucamwebauth/templates/ucamwebauth_403.html
ucamwebauth/templates/ucamwebauth_500.html
django_ucamwebauth-2.0.0.dist-info/AUTHORS
django_ucamwebauth-2.0.0.dist-info/LICENSE
django_ucamwebauth-2.0.0.dist-info/METADATA
django_ucamwebauth-2.0.0.dist-info/WHEEL
django_ucamwebauth-2.0.0.dist-info/top_level.txt
django_ucamwebauth-2.0.0.dist-info/RECORD
