Metadata-Version: 2.1
Name: django-ucamwebauth
Version: 2.0.0
Summary: A Django authentication backend for Ucam-WebAuth a.k.a. Raven
Home-page: https://gitlab.developers.cam.ac.uk/uis/devops/django/ucamwebauth
Author: DevOps Division, University Information Services, University of Cambridge
Author-email: raven-support@cam.ac.uk
License: MIT
Platform: UNKNOWN
Classifier: Development Status :: 5 - Production/Stable
Classifier: Environment :: Web Environment
Classifier: Framework :: Django
Classifier: Intended Audience :: Developers
Classifier: License :: OSI Approved :: MIT License
Classifier: Operating System :: OS Independent
Classifier: Programming Language :: Python
Requires-Python: >=3.7
License-File: LICENSE
License-File: AUTHORS
Requires-Dist: django (<5,>=3.2)
Requires-Dist: pyOpenSSL
Requires-Dist: requests
